README
setup.py
src/mlf.py
src/mailing_list_filter.egg-info/PKG-INFO
src/mailing_list_filter.egg-info/SOURCES.txt
src/mailing_list_filter.egg-info/dependency_links.txt
src/mailing_list_filter.egg-info/top_level.txt
src/mailing_list_filter.egg-info/zip-safe