Metadata-Version: 1.0
Name: mailing-list-filter
Version: 0.1
Summary: Mailing List Filter
Home-page: http://assorted.sourceforge.net/mailing-list-filter/
Author: Yang Zhang
Author-email: yaaang NOSPAM at REMOVECAPS gmail
License: Python Software Foundation License
Download-URL: http://pypi.python.org/pypi/mailing-list-filter/
Keywords: mailing,list,email,filter,IMAP,Gmail
Platform: any
Classifier: Development Status :: 4 - Beta
Classifier: Environment :: No Input/Output (Daemon)
Classifier: Intended Audience :: End Users/Desktop
Classifier: License :: OSI Approved :: Python Software Foundation License
Classifier: Operating System :: OS Independent
Classifier: Programming Language :: Python
Classifier: Topic :: Communications :: Email
